{
  "type": "bundle",
  "id": "bundle--b56c1e2e-a40c-44ca-83dd-09e25936d273",
  "spec_version": "2.0",
  "objects": [
    {
      "type": "identity",
      "id": "identity--611d9d41-dba5-4e13-9b29-e22488058ffc",
      "created": "2017-04-14T13:07:49.812Z",
      "modified": "2017-04-14T13:07:49.812Z",
      "name": "Stark Industries",
      "identity_class": "organization",
      "contact_information": "info@stark.com",
      "sectors": [
        "defense"
      ],
    },
    {
      "type": "marking-definition",
      "id": "marking-definition--05ac6c05-8b38-43f2-996d-e6715571090b",
      "created": "2017-04-14T13:07:49.812Z",
      "modified": "2017-04-14T13:07:49.812Z",
      "created_by_ref": "identity--611d9d41-dba5-4e13-9b29-e22488058ffc",
      "definition_type": "tlp",
      "definition": {
        "tlp": "amber"
      }
    },
    {
      "type": "marking-definition",
      "id": "marking-definition--d771aceb-3148-4315-b4b4-130b888533d0",
      "created": "2017-04-14T13:07:49.812Z",
      "modified": "2017-04-14T13:07:49.812Z",
      "created_by_ref": "identity--611d9d41-dba5-4e13-9b29-e22488058ffc",
      "definition_type": "statement",
      "definition": {
        "statement": "Copyright © Stark Industries 2017."
      }
    },
    {
      "type": "indicator",
      "id": "indicator--33fe3b22-0201-47cf-85d0-97c02164528d",
      "created": "2017-04-14T13:07:49.812Z",
      "modified": "2017-04-14T13:07:49.812Z",
      "created_by_ref": "identity--611d9d41-dba5-4e13-9b29-e22488058ffc",
      "name": "Known malicious IP Address",
      "labels": [
        "malicious-activity"
      ],
      "pattern": "[ipv4addr:value = '10.0.0.0']",
      "valid_from": "2017-04-14T13:07:49.812Z",
      "object_marking_refs": [
        "marking-definition--05ac6c05-8b38-43f2-996d-e6715571090b",
        "marking-definition--d771aceb-3148-4315-b4b4-130b888533d0"
      ]
    }
  ]
}
